stack_pr-0.1.6.dist-info/METADATA
stack_pr-0.1.6.dist-info/WHEEL
stack_pr-0.1.6.dist-info/entry_points.txt
stack_pr-0.1.6.dist-info/licenses/LICENSE
stack_pr/__init__.py
stack_pr/__main__.py
stack_pr/cli.py
stack_pr/git.py
stack_pr/py.typed
stack_pr/shell_commands.py
stack_pr-0.1.6.dist-info/RECORD
