Metadata-Version: 2.1
Name: stack-pr
Version: 0.1.6
Summary: Stacked PR CLI for Github
Keywords: stacked-prs,github,pull-requests,stack-pr,git,version-control
Author-Email: Modular Inc <hello@modular.com>
Maintainer-Email: Modular Inc <hello@modular.com>
License: ==============================================================================================
Classifier: Development Status :: 5 - Production/Stable
Classifier: Intended Audience :: Developers
Classifier: Topic :: Software Development :: Version Control :: Git
Classifier: License :: OSI Approved :: Apache Software License
Classifier: Operating System :: OS Independent
Classifier: Environment :: Console
Classifier: Topic :: Utilities
Classifier: Programming Language :: Python
Classifier: Programming Language :: Python :: 3.9
Classifier: Programming Language :: Python :: 3.10
Classifier: Programming Language :: Python :: 3.11
Classifier: Programming Language :: Python :: 3.12
Classifier: Programming Language :: Python :: 3.13
Project-URL: Homepage, https://github.com/modular/stack-pr
Project-URL: Repository, https://github.com/modular/stack-pr
Project-URL: Bug Tracker, https://github.com/modular/stack-pr/issues
Requires-Python: >=3.9
Requires-Dist: typing_extensions; python_version < "3.13"
Provides-Extra: dev
Requires-Dist: pytest; extra == "dev"
Requires-Dist: pytest-mock; extra == "dev"
Requires-Dist: mypy; extra == "dev"
Requires-Dist: ruff; extra == "dev"
